{
  "name": "instrument/Agong.png",
  "bucket": "mossem-dfa21.appspot.com",
  "contentType": "image/png",
  "metageneration": 1,
  "generation": 1627092067823,
  "storageClass": "STANDARD",
  "etag": "someETag",
  "contentDisposition": "inline",
  "contentEncoding": "identity",
  "downloadTokens": [
    "6bab9650-24e7-4316-bb68-0d2d37a53c3e"
  ],
  "timeCreated": "2021-07-24T02:01:07.822Z",
  "updated": "2021-07-24T02:01:07.826Z",
  "size": 374813,
  "md5Hash": "pg2c7vrfrMC846XmyO/0Vw==",
  "crc32c": "2299640211"
}